sp_ask_school_data_crunching/__init__.py
sp_ask_school_data_crunching/analytics/__init__.py
sp_ask_school_data_crunching/analytics/school_analytics.py
sp_ask_school_data_crunching/analytics/service_analytics.py
sp_ask_school_data_crunching/analytics.py
sp_ask_school_data_crunching/api_client.py
sp_ask_school_data_crunching/data_processing.py
sp_ask_school_data_crunching/fetch_chats.py
sp_ask_school_data_crunching/utils.py
sp_ask_school_data_crunching-0.1.2.dist-info/entry_points.txt
sp_ask_school_data_crunching-0.1.2.dist-info/METADATA
sp_ask_school_data_crunching-0.1.2.dist-info/WHEEL
sp_ask_school_data_crunching-0.1.2.dist-info/RECORD
