Metadata-Version: 2.1
Name: sp-ask-school-data-crunching
Version: 0.1.2
Summary: Collection of scripts for data analytics of Ask Data Through LibraryH3lp API - metadata only
Home-page: https://github.com/scholarsportal/sp_ask_school_data_crunching
License: MIT
Keywords: libraryh3lp,chat,analytics,scholars portal,ask a librarian,Scholars Portal,OCUL
Author: Guinslym
Author-email: guinslym@gmail.com
Requires-Python: >=3.10,<4.0
Classifier: License :: OSI Approved :: MIT License
Classifier: Operating System :: MacOS :: MacOS X
Classifier: Operating System :: POSIX :: Linux
Classifier: Operating System :: Unix
Classifier: Programming Language :: Python :: 3
Classifier: Programming Language :: Python :: 3.10
Classifier: Programming Language :: Python :: 3.11
Requires-Dist: lh3api (>=0.2.0,<0.3.0)
Requires-Dist: numpy (>=2.1.3,<3.0.0)
Requires-Dist: pandas (>=2.2.3,<3.0.0)
Requires-Dist: plotly (>=5.24.1,<6.0.0)
Requires-Dist: python-dotenv (>=1.0.1,<2.0.0)
Requires-Dist: scipy (>=1.14.1,<2.0.0)
Requires-Dist: sp-ask-chats-utils (>=0.1.2,<0.2.0)
Requires-Dist: sp-ask-report-chats-per-school (>=0.1.4,<0.2.0)
Requires-Dist: sp-ask-school (>=0.3.9,<0.4.0)
Requires-Dist: sp-lh3-constant-contact (>=0.1.6,<0.2.0)
Project-URL: Documentation, https://github.com/scholarsportal/sp_ask_school_data_crunching#readme
Project-URL: Repository, https://github.com/scholarsportal/sp_ask_school_data_crunching
